{
	"list": [
		{
			"id": "7e7ff095-5a47-40ff-8419-10a5fd379d07",
			"type": "Programador",
			"name": "Tiago Danin",
			"photo": "https://avatars1.githubusercontent.com/u/5731176?s=460",
			"description": "Faço programas para computador"
		}
	],
	"banksCpf": [],
	"request": [
		{
			"id": "4333ff095-3223-40ff-8419-10a5fd379d07",
			"userId": "7e7ff095-5a47-40ff-8419-10a5fd379d07",
			"name": "Criar um jogo estilo Minecraft",
			"description": "Lorem ipsum dolor sit amet, consetetur sadipscing elitr, sed diam nonumy eirmod tempor invidunt ut labore et dolore magna aliquyam erat, sed diam voluptua. At vero eos et accusam et justo duo dolores et ea rebum. Stet clita kasd gubergren, no sea takimata sanctus est Lorem ipsum dolor sit amet. Lorem ipsum dolor sit amet, consetetur sadipscing elitr, sed diam",
			"date": "05/08/2020",
			"amount": "80,00"
		},
		{
			"id": "7e432343-3223-40ff-8419-10a5fd379d07",
			"userId": "7e7ff095-5a47-40ff-8419-10a5fd379d07",
			"name": "Criar um programar que faz dinheiro",
			"description": "Lorem ipsum dolor sit amet, consetetur sadipscing elitr, sed diam nonumy eirmod tempor invidunt ut labore et dolore magna aliquyam erat, sed diam voluptua. At vero eos et accusam et justo duo dolores et ea rebum. Stet clita kasd gubergren, no sea takimata sanctus est Lorem ipsum dolor sit amet. Lorem ipsum dolor sit amet, consetetur sadipscing elitr, sed diam",
			"date": "07/08/2020",
			"amount": "220,01"
		}
	]
}
